{"productData":{
    "name": "Maths Book",
    "category":"books",
    "description": "Engineering Mathematics 1",
    "price": 10.99,
    "image": "https://i.picsum.photos/id/1010/5184/3456.jpg"
},
"userData":{
    "email":"sheldon@gmail.com",
    "username":"sheldon",
    "password":"bazinga",
    "name": {
        "firstname":"Sheldon",
        "lastname":"Cooper"
    },
    "address": {
        "city":"Texas",
        "street":"south street",
        "number": 3,
        "zipcode":"91001",
        "geolocation": {
            "lat":"-46.3159",
            "long":"71.1496"
        }
    },
    "phone":"1-570-236-7033"
    },
    "userData2":{
        "name": {
            "firstname": "sasi",
            "lastname": "dharan"
        },
        "address": {
            "geolocation": {
                "lat": "-46.3159",
                "long": "71.1496"
            },
            "city": "Texas",
            "street": "south street",
            "number": 3,
            "zipcode": "91001"
        },
        "userId": 2,
        "email": "sasi@gmail.com",
        "password":"hello",
        "username": "sasi",
        "phone": "1-570-236-7033"
    },
    "cartData":{
        "userId":1,
        "products": [
            {
                "productId": 16,
                "quantity": 1
            }
        ]
    }
}